soccer_data_api/__init__.py
soccer_data_api/config.py
soccer_data_api/get_soccer_data.py
soccer_data_api/response_types.py
soccer_data_api/soccer_api.py
soccer_data_api/soccer_data_api.py
soccer_data_api/test.py
soccer_data_api-0.5.6.dist-info/LICENSE
soccer_data_api-0.5.6.dist-info/METADATA
soccer_data_api-0.5.6.dist-info/WHEEL
soccer_data_api-0.5.6.dist-info/top_level.txt
soccer_data_api-0.5.6.dist-info/RECORD
