Metadata-Version: 2.1
Name: soccer-data-api
Version: 0.5.6
Summary: A Python web-scrap package to get soccer data/stats.
Home-page: https://github.com/reppon97/soccer-data-api
Author: Rejep Mammedov
Author-email: reppon97@gmail.com
License: MIT
Platform: UNKNOWN
Classifier: License :: OSI Approved :: MIT License
